pyconn/__init__.py
pyconn/slack.py
pyconn/common/__init__.py
pyconn/common/util.py
pyconn/db/__init__.py
pyconn/db/advancedqreader.py
pyconn/db/kdb.py
pyconn/db/oracle.py
pyconn/db/qpool.py
pyconn/file/__init__.py
pyconn/file/csv.py
pyconn/file/excel.py
pyconn/wx/__init__.py
pyconn/wx/config.py
pyconn/wx/wechat.py
pyconn-0.2.3.dist-info/LICENSE
pyconn-0.2.3.dist-info/METADATA
pyconn-0.2.3.dist-info/WHEEL
pyconn-0.2.3.dist-info/top_level.txt
pyconn-0.2.3.dist-info/RECORD
