Metadata-Version: 2.1
Name: pyconn
Version: 0.2.3
Summary: python connection tools collection
Home-page: 
Author: luoanni
Author-email: luoanni33@gmail.com
License: Copyright (c) 2016, James Liu        
Platform: UNKNOWN
License-File: LICENSE
Requires-Dist: qPython3 (>=1.0.0)
Requires-Dist: numpy
Requires-Dist: pandas
